neoaria/__init__.py
neoaria/__version__.py
neoaria/archive.py
neoaria/commons.py
neoaria/microsoft.py
neoaria/middleware.py
neoaria/pdf.py
neoaria/contents/__init__.py
neoaria/contents/process_business.py
neoaria/models/__init__.py
neoaria/models/rms.py
neoaria/models/translation.py
neoaria_commons-0.2.93.dist-info/METADATA
neoaria_commons-0.2.93.dist-info/WHEEL
neoaria_commons-0.2.93.dist-info/top_level.txt
neoaria_commons-0.2.93.dist-info/RECORD
