Metadata-Version: 2.1
Name: neoaria-commons
Version: 0.2.93
Summary: neoaria commons module for neoaria-backend-generator
Home-page: https://www.neoaria.io
Author: yakenator
Author-email: yakenator@neoaria.io
License: MIT License
Classifier: Environment :: Web Environment
Classifier: Framework :: FastAPI
Classifier: Intended Audience :: Developers
Classifier: License :: OSI Approved :: MIT License
Classifier: Operating System :: OS Independent
Classifier: Programming Language :: Python
Classifier: Programming Language :: Python :: 3
Classifier: Programming Language :: Python :: 3.12
